libname/__init__.py
libname/addup.py
libname/quicklookts09.py
addup-0.0.2.dist-info/LICENSE.txt
addup-0.0.2.dist-info/METADATA
addup-0.0.2.dist-info/WHEEL
addup-0.0.2.dist-info/top_level.txt
addup-0.0.2.dist-info/RECORD
