Metadata-Version: 2.1
Name: addup
Version: 0.0.2
Summary: addup
Home-page: UNKNOWN
Author: Hong Tang
Author-email: <stanghong@gmail.com>
License: UNKNOWN
Keywords: python,test,plot
Platform: UNKNOWN
Classifier: Development Status :: 1 - Planning
Classifier: Intended Audience :: Developers
Classifier: Programming Language :: Python :: 3
Classifier: Operating System :: Unix
Classifier: Operating System :: MacOS :: MacOS X
Classifier: Operating System :: Microsoft :: Windows
License-File: LICENSE.txt
Requires-Dist: numpy
Requires-Dist: pandas
